ebcommander/__init__.py
ebcommander/__main__.py
ebcommander/ebcommander.py
ebcommander-1.0.1.dist-info/LICENSE
ebcommander-1.0.1.dist-info/METADATA
ebcommander-1.0.1.dist-info/WHEEL
ebcommander-1.0.1.dist-info/top_level.txt
ebcommander-1.0.1.dist-info/RECORD
