Metadata-Version: 2.1
Name: ebcommander
Version: 1.0.1
Summary: Elektrobit Command Python interface
Home-page: https://github.com/monstermichl/ebcommander.git
Author: monstermichl
License: UNKNOWN
Keywords: elektrobit,eb,command,ebcommand
Platform: UNKNOWN
Classifier: Programming Language :: Python :: 3
Classifier: License :: OSI Approved :: MIT License
Classifier: Operating System :: OS Independent
Requires-Python: >=3.7
License-File: LICENSE
Requires-Dist: requests
Requires-Dist: pyyaml
Requires-Dist: beautifulsoup4
